[
  {
    "id": "2063933889828274475",
    "text": "📢速報！📢\n☕️JumpingKiss Lunch Meeting in Nagoya☕️\n📅6月13日（土）\n⏰12時30分〜\n🍽️会場：名古屋市内某所（お洒落なイタリアンのお店です！）、\n💰参加費：12,000円\n🎁記念写真3枚付き\n⚠️先着10名様限定！\n＊お店の場所などの詳細はお申し込みされた方にメールにてご連絡します。\n🎟️ご予約は→ t-dv.com/lunch_meeting_0613\n🎫受付期間：6月9日（火）23時〜\n#JumpingKiss",
    "post_url": "https://nitter.net/jumpingkiss/status/2063933889828274475#m",
    "created_at": "Mon, 08 Jun 2026 10:39:20 GMT",
    "image_url": "https://nitter.net/pic/media%2FHKSQ1uwbIAAMqgg.jpg"
  },
  {
    "id": "2063593928142786784",
    "text": "📢名古屋遠征オフ会のお知らせ📢\n12時過ぎから、栄駅からライブハウスまでの途中のお店でランチミーティング開催予定です！\n詳細は明日お知らせします！",
    "post_url": "https://nitter.net/jumpingkiss/status/2063593928142786784#m",
    "created_at": "Sun, 07 Jun 2026 12:08:26 GMT",
    "image_url": null
  },
  {
    "id": "2063588183862911316",
    "text": "📢速報！📢\n📸Nagoya Rainy Season Photo Shoot📸\n📅6月14日（日）\n⛲️場所：名古屋市内（詳しくはお申し込みされた方にメールでお知らせします）\n⏰集合時間：14時20分\n⛲️集合場所：（詳しくはお申し込みされた方にメールでお知らせします）\n💰参加費：10,000円\n🎁記念写真撮影券２枚付き\n✨途中チェキタイムあり（一枚1500円）\n🎟️ご予約は→ t-dv.com/photo_shoot_nagoya_…\n🎫受付期間：6月9日（火）23時〜6月12日（金）23時59分\n#JumpingKiss",
    "post_url": "https://nitter.net/jumpingkiss/status/2063588183862911316#m",
    "created_at": "Sun, 07 Jun 2026 11:45:37 GMT",
    "image_url": "https://nitter.net/pic/media%2FHKNWaDvbgAA0i6O.jpg"
  },
  {
    "id": "2063587833055703239",
    "text": "📢速報！📢\n📸Nagoya Rainy Season Photo Shoot📸\n📅6月13日（土）\n⛲️場所：名古屋市内（詳しくはお申し込みされた方にメールでお知らせします）\n⏰集合時間：16時40分\n⛲️集合場所：（詳しくはお申し込みされた方にメールでお知らせします）\n💰参加費：10,000円\n🎁記念写真撮影券２枚付き\n✨途中チェキタイムあり（一枚1500円）\n🎟️ご予約は→ t-dv.com/photo_shoot_nagoya_…\n🎫受付期間：6月8日（月）23時〜6月12日（金）23時59分\n#JumpingKiss",
    "post_url": "https://nitter.net/jumpingkiss/status/2063587833055703239#m",
    "created_at": "Sun, 07 Jun 2026 11:44:13 GMT",
    "image_url": "https://nitter.net/pic/media%2FHKNWAeiakAAWk6O.jpg"
  },
  {
    "id": "2063426212572135578",
    "text": "📢今日の3本目は！📢\n🍑桃色革命✖Jumping Kiss 至高のノンストップツーマン🎤\n📅6月7日（日）\n🎪原宿GE Theater\n⏰16:45開場/17:00開演\n👥出演：桃色革命/Jumping Kiss\n🥤1Drink別途\n💰①SSチケット［最前確約 限定10席］6,000円\n💰②Sチケット［前方エリア］3,500円\n🆓③Aチケット（無料）［後方エリア］0円\n🎟️チケット→ t-dv.com/260607nonstop\n#JumpingKiss",
    "post_url": "https://nitter.net/jumpingkiss/status/2063426212572135578#m",
    "created_at": "Sun, 07 Jun 2026 01:02:00 GMT",
    "image_url": "https://nitter.net/pic/media%2FHKI4tsMaAAEQcjN.jpg"
  },
  {
    "id": "2063425960570147106",
    "text": "📢今日の2本目は！📢\n💣ワンコインBOMBER!!💣\n📅6月7日（日）\n🎪原宿GE Theater\n⏰11:45開場 / 12:00開演\n🎤JumpingKiss 14:50~15:15\n⏰特典会　15:15~16:15【5階ブースB】\n🥤1Drink別途\n💰①SSチケット　6,000円（最前確約）※限定10席\n💰②Sチケット　3,500円\n💰③Aチケット　500円\n🎟️チケット→ t-dv.com/260607ge\n※5/31 22:00-発売\n【配信チケット】※生配信＆アーカイブ2週間\ntiget.net/events/494660\n#JumpingKiss",
    "post_url": "https://nitter.net/jumpingkiss/status/2063425960570147106#m",
    "created_at": "Sun, 07 Jun 2026 01:01:00 GMT",
    "image_url": "https://nitter.net/pic/media%2FHKI4Q_haAAAT9ex.jpg"
  },
  {
    "id": "2063425714406199568",
    "text": "📢今日の1本目は！📢\n🏫帰ってきたアトリエクラブ〜JK学園・五反田校〜3時間目！🏫\n📅6月7日（日）\n🎪五反田G6（〒141-0031 東京都品川区西五反田２丁目６−３ 東洋ビル B1）\n⏰開場：11時00分\n📚開演：11時15分〜\n💰着席最前列（🎁メンバーの成績表付）6,000円\n⚠️15名様限定\n📸静止画＆動画OK（動画はスマホでの撮影のみとなります。）\n💰着席2列目（🎁メンバーの成績表付）5,000円\n⚠️10名様限定\n📸静止画のみ/動画NG\n💰スタンディングエリア（静止画のみ/動画NG）2,000円\n🔰🆓JumpingKiss単独公演が初めての方限定：0円（エリアはスタンディングになります）\n＊1Drink別途　＊当日券は+500円\n🎟️詳細は→ t-dv.com/atorie_gotanda_0607\n#JumpingKiss",
    "post_url": "https://nitter.net/jumpingkiss/status/2063425714406199568#m",
    "created_at": "Sun, 07 Jun 2026 01:00:01 GMT",
    "image_url": "https://nitter.net/pic/media%2FHKI33iKagAAsRXF.jpg"
  },
  {
    "id": "2063063824597422300",
    "text": "📢今日の3本目は！📢\n🌈無銭ぷろじぇくと!! vol.78🌈\n📅6月6日(土)\n🎪GOTANDA G6\n⏰開場/開演：9:40/9:50\n🎤JumpingKiss 20:00~20:20\n⏰特典会　20:25~21:25\n💰通常エリアチケット：0円\n💰前方エリアチケット：2,500円\n💰当日チケット：各種+1,000円\n※各種+2ドリンク\n■再入場：可能（無料）\n🎟️チケット→ paylove.org/events/1687\n#JumpingKiss",
    "post_url": "https://nitter.net/jumpingkiss/status/2063063824597422300#m",
    "created_at": "Sat, 06 Jun 2026 01:02:00 GMT",
    "image_url": "https://nitter.net/pic/media%2FHKDcktpasAAUUQ_.jpg"
  },
  {
    "id": "2063063572851359861",
    "text": "📢今日の2本目は！📢\n🍑桃色革命✖Jumping Kiss 至高のノンストップツーマン🎤\n📅6月6日（土）\n🎪原宿GE Theater\n⏰16:45開場/17:00開演\n👥出演：桃色革命/Jumping Kiss\n🥤1Drink別途\n💰①SSチケット［最前確約 限定10席］6,000円\n💰②Sチケット［前方エリア］3,500円\n🆓③Aチケット（無料）［後方エリア］0円\n🎟️チケット→ t-dv.com/260606nonstop\n▶発売日　一般（先着） 2026/05/31 22:00-\n#JumpingKiss",
    "post_url": "https://nitter.net/jumpingkiss/status/2063063572851359861#m",
    "created_at": "Sat, 06 Jun 2026 01:01:00 GMT",
    "image_url": "https://nitter.net/pic/media%2FHKDcS9XaYAA0DGN.jpg"
  },
  {
    "id": "2063063323118342329",
    "text": "📢今日の1本目は！📢\n💣ワンコインBOMBER!!💣\n📅6月6日（土）\n🎪原宿GE Theater\n⏰11:00開場 / 11:15開演\n🎤JumpingKiss 14:25~14:50\n⏰特典会　14:50~15:50【5階ブースD】\n🥤1Drink別途\n💰①SSチケット　6,000円（最前確約）※限定10席\n💰②Sチケット　3,500円\n💰③Aチケット　500円\n🎟️チケット→ t-dv.com/260606ge\n※5/31 22:00-発売\n【配信チケット】※生配信＆アーカイブ2週間\ntiget.net/events/494659\n#JumpingKiss",
    "post_url": "https://nitter.net/jumpingkiss/status/2063063323118342329#m",
    "created_at": "Sat, 06 Jun 2026 01:00:00 GMT",
    "image_url": "https://nitter.net/pic/media%2FHKDcLjka4AAyYhu.jpg"
  },
  {
    "id": "2062535299910271107",
    "text": "📢出演します！📢\n💣ワンコインBOMBER!!💣\n📅6月21日（日）\n🎪GOTANDA G2\n⏰10:00開場 / 10:15開演\n🎤タイムテーブルは続報をお待ちください。\n🥤1Drink別途\n💰①Sチケット　5,000円\n💰②Aチケット　500円\n🎟️チケット→ t-dv.com/260621g2\n※6/5 10:00-発売\n#JumpingKiss",
    "post_url": "https://nitter.net/jumpingkiss/status/2062535299910271107#m",
    "created_at": "Thu, 04 Jun 2026 14:01:50 GMT",
    "image_url": "https://nitter.net/pic/media%2FHJ-YeCHbIAEgPUF.jpg"
  },
  {
    "id": "2062534671158870094",
    "text": "📢出演します！📢\n💣ワンコインBOMBER!!💣\n📅6月20日（土）\n🎪GOTANDA G2\n⏰10:00開場 / 10:15開演\n🎤タイムテーブルは続報をお待ちください。\n🥤1Drink別途\n💰①Sチケット　5,000円\n💰②Aチケット　500円\n🎟️チケット→ t-dv.com/260620g2\n※6/5 10:00-発売\n#JumpingKiss",
    "post_url": "https://nitter.net/jumpingkiss/status/2062534671158870094#m",
    "created_at": "Thu, 04 Jun 2026 13:59:20 GMT",
    "image_url": "https://nitter.net/pic/media%2FHJ-XsHVawAAsyI_.jpg"
  },
  {
    "id": "2062155771274760586",
    "text": "📢出演します！📢\n🌈Jumping Kiss東京定期公演 ジャンキスやねん！Vol.72🌈\n📅7月12日(日)\n🎪シダックスカルチャーホール\n⏰開場18:05/開演18:15～19:05(50分)\n📸撮影条件：全曲撮影可能 動画NG\n💰通常2500円/優先5000円\n※優先チケット20枚\n※優先チケット特典:お好きなメンバーを1分間動画撮影(特典会の最初にて)\n🎟️チケット→ t-dv.com/igeki202670120000\n#JumpingKiss",
    "post_url": "https://nitter.net/jumpingkiss/status/2062155771274760586#m",
    "created_at": "Wed, 03 Jun 2026 12:53:43 GMT",
    "image_url": "https://nitter.net/pic/media%2FHJ4_TpPaUAAP_Xm.jpg"
  },
  {
    "id": "2062154130182013233",
    "text": "📢タイテ公開中！📢\n💣ワンコインBOMBER!!💣\n📅6月7日（日）\n🎪原宿GE Theater\n⏰11:45開場 / 12:00開演\n🎤JumpingKiss 14:50~15:15\n⏰特典会　15:15~16:15【5階ブースB】\n🥤1Drink別途\n💰①SSチケット　6,000円（最前確約）※限定10席\n💰②Sチケット　3,500円\n💰③Aチケット　500円\n🎟️チケット→ t-dv.com/260607ge\n※5/31 22:00-発売\n【配信チケット】※生配信＆アーカイブ2週間\ntiget.net/events/494660\n#JumpingKiss",
    "post_url": "https://nitter.net/jumpingkiss/status/2062154130182013233#m",
    "created_at": "Wed, 03 Jun 2026 12:47:12 GMT",
    "image_url": "https://nitter.net/pic/media%2FHJ4-AB4aIAAczvh.jpg"
  }
]
