[
  {
    "id": "stainy-2026-05-11-live-marquee--625f7a1c",
    "group_id": "stainy",
    "type": "live",
    "title": "MARQUEE祭",
    "date": "2026-05-11",
    "description": "MARQUEE祭",
    "created_at": "2026-06-04T01:09:30.191Z"
  },
  {
    "id": "stainy-2026-05-13-live-leading-umikaze-1fd9445b",
    "group_id": "stainy",
    "type": "live",
    "title": "LEADING UMIKAZE",
    "date": "2026-05-13",
    "description": "LEADING UMIKAZE",
    "created_at": "2026-06-04T01:09:30.191Z"
  },
  {
    "id": "stainy-2026-05-16-live-summer-jungle-491ad058",
    "group_id": "stainy",
    "type": "live",
    "title": "SUMMER JUNGLE",
    "date": "2026-05-16",
    "description": "SUMMER JUNGLE",
    "created_at": "2026-06-04T01:09:30.191Z"
  },
  {
    "id": "stainy-2026-05-17-live---45963476",
    "group_id": "stainy",
    "type": "live",
    "title": "リリースツアー名古屋",
    "date": "2026-05-17",
    "description": "リリースツアー名古屋",
    "created_at": "2026-06-04T01:09:30.191Z"
  },
  {
    "id": "stainy-2026-05-24-live---3cafb946",
    "group_id": "stainy",
    "type": "live",
    "title": "リリースイベント名古屋",
    "date": "2026-05-24",
    "description": "リリースイベント名古屋",
    "created_at": "2026-06-04T01:09:30.191Z"
  },
  {
    "id": "stainy-ticket-2026-05-30-sweet-partt",
    "group_id": "stainy",
    "type": "ticket",
    "title": "SWEET PARTT チケ発",
    "date": "2026-05-30",
    "time_start": "22:30",
    "related_event_id": "stainy-2026-06-26-sweet-partt",
    "ticket_url": "https://livepocket.jp/e/sweetparty_selene",
    "post_url": "https://nitter.net/STAiNY_official/status/2060323359335063633#m",
    "created_at": "2026-05-29T11:32:22Z"
  },
  {
    "id": "stainy-2026-05-30-ticket-sweet-partt-e793dc6a",
    "group_id": "stainy",
    "type": "ticket",
    "title": "「SWEET PARTT」 チケ発",
    "date": "2026-05-30",
    "time_start": "22:30",
    "post_url": "https://nitter.net/STAiNY_official/status/2060323359335063633#m",
    "image_url": "https://nitter.net/pic/media%2FHJe9K9kbMAA3TAn.jpg",
    "created_at": "2026-05-29T11:32:22Z"
  },
  {
    "id": "stainy-2026-05-30-ticket-sweet-partt-4351cc5f",
    "group_id": "stainy",
    "type": "ticket",
    "title": "SWEET PARTT チケ発",
    "date": "2026-05-30",
    "time_start": "22:30",
    "post_url": "https://nitter.net/STAiNY_official/status/2060323359335063633#m",
    "image_url": "https://nitter.net/pic/media%2FHJe9K9kbMAA3TAn.jpg",
    "created_at": "2026-05-29T11:32:22Z"
  },
  {
    "id": "stainy-ticket-2026-06-02-sawayaka-date",
    "group_id": "stainy",
    "type": "ticket",
    "title": "爽やかデート私服公演 チケ発",
    "date": "2026-06-02",
    "time_start": "22:00",
    "related_event_id": "stainy-2026-06-12-sawayaka-date",
    "ticket_url": "https://t-dv.com/STAiNY0612",
    "post_url": "https://nitter.net/STAiNY_official/status/2061403523267575825#m",
    "created_at": "2026-06-01T11:04:33Z"
  },
  {
    "id": "stainy-2026-06-02-deadline-event-34b68507",
    "group_id": "stainy",
    "type": "deadline",
    "title": "プレミアムライブ参加申込みのご案内 締切",
    "date": "2026-06-02",
    "time_start": "22:00",
    "description": "【プレミアムライブ参加申込みのご案内】 / 日頃よりSTAiNYを応援して頂き誠にありがとうございます。 / プレミアムライブのご案内になります。 / ポイントカード250ポイントを達成されたお客様で、「プレミアムライブ」へのご参加を希望される方は、下記フォームよりお申込みをお願いいたします。",
    "ticket_url": "https://nitter.net/STAiNY_official/status/2061403523267575825#m",
    "post_url": "https://nitter.net/STAiNY_official/status/2061800688213172410#m",
    "image_url": "https://nitter.net/pic/card_img%2F2061800690167771136%2FztnULKDj%3Fformat%3Djpg%26name%3D420x420_2",
    "created_at": "2026-06-02T13:22:45Z"
  },
  {
    "id": "stainy-2026-06-02-ticket-event-bd701e09",
    "group_id": "stainy",
    "type": "ticket",
    "title": "｢爽やかデート私服公演」 チケ発",
    "date": "2026-06-02",
    "time_start": "22:00",
    "post_url": "https://nitter.net/STAiNY_official/status/2061403523267575825#m",
    "image_url": "https://nitter.net/pic/media%2FHJuTk6laoAA3iWk.jpg",
    "created_at": "2026-06-01T11:04:33Z"
  },
  {
    "id": "stainy-2026-06-02-deadline-event-dea34bf9",
    "group_id": "stainy",
    "type": "deadline",
    "title": "プレミアムライブ 締切",
    "date": "2026-06-02",
    "time_start": "22:00",
    "description": "【プレミアムライブ参加申込みのご案内】 / 日頃よりSTAiNYを応援して頂き誠にありがとうございます。 / プレミアムライブのご案内になります。 / ポイントカード250ポイントを達成されたお客様で、「プレミアムライブ」へのご参加を希望される方は、下記フォームよりお申込みをお願いいたします。",
    "ticket_url": "https://nitter.net/STAiNY_official/status/2061403523267575825#m",
    "post_url": "https://nitter.net/STAiNY_official/status/2061800688213172410#m",
    "image_url": "https://nitter.net/pic/card_img%2F2061800690167771136%2FztnULKDj%3Fformat%3Djpg%26name%3D420x420_2",
    "created_at": "2026-06-02T13:22:45Z"
  },
  {
    "id": "stainy-ticket-2026-06-03-himari-birthday",
    "group_id": "stainy",
    "type": "ticket",
    "title": "佐々木ひまり生誕祭 チケ発",
    "date": "2026-06-03",
    "time_start": "22:00",
    "related_event_id": "stainy-2026-06-21-himari-birthday",
    "ticket_url": "https://ticketdive.com/event/STAiNY0621",
    "post_url": "https://nitter.net/STAiNY_official/status/2061749699728863301#m",
    "created_at": "2026-06-02T10:00:08Z"
  },
  {
    "id": "stainy-2026-06-03-ticket-event-5d8bde45",
    "group_id": "stainy",
    "type": "ticket",
    "title": "「佐々木ひまり生誕祭」 チケ発",
    "date": "2026-06-03",
    "time_start": "22:00",
    "post_url": "https://nitter.net/STAiNY_official/status/2061749699728863301#m",
    "image_url": "https://nitter.net/pic/media%2FHJzOaMIbIAEHNa6.jpg",
    "created_at": "2026-06-02T10:00:08Z"
  },
  {
    "id": "stainy-2026-06-03-ticket-event-0eddbb71",
    "group_id": "stainy",
    "type": "ticket",
    "title": "佐々木ひまり生誕祭 チケ発",
    "date": "2026-06-03",
    "time_start": "22:00",
    "post_url": "https://nitter.net/STAiNY_official/status/2061749699728863301#m",
    "image_url": "https://nitter.net/pic/media%2FHJzOaMIbIAEHNa6.jpg",
    "created_at": "2026-06-02T10:00:08Z"
  },
  {
    "id": "stainy-2026-06-06-okinawa-girls-girls-day1",
    "group_id": "stainy",
    "type": "live",
    "title": "OKINAWA GIRLS GIRLS",
    "date": "2026-06-06",
    "time_start": "12:50",
    "time_end": "13:20",
    "venue": "那覇文化会館 なはーと小ホール",
    "benefit_time": "13:30-14:40(D)",
    "ticket_url": "http://tiget.net/events/486723",
    "description": "各: 2s写メ券+2pt(前方+15秒動画)",
    "post_url": "https://nitter.net/STAiNY_official/status/2060316558610849853#m",
    "created_at": "2026-05-29T11:05:21Z"
  },
  {
    "id": "stainy-2026-06-06-puchi-offkai",
    "group_id": "stainy",
    "type": "free",
    "title": "プチオフ会開催",
    "date": "2026-06-06",
    "time_open": "18:00",
    "time_start": "18:30",
    "venue": "瀬長島ビーチ / うみかぜテラス前",
    "price": "無料 / 花火一回 2,000円（写メ付き）",
    "description": "沖縄で花火をしながらゆったり過ごすオフ会。雨天の場合は中止の可能性あり。",
    "post_url": "https://nitter.net/STAiNY_official/status/2061734772427374864#m",
    "created_at": "2026-06-02T09:00:49Z"
  },
  {
    "id": "stainy-2026-06-06-free-event-c2c8e768",
    "group_id": "stainy",
    "type": "free",
    "title": "🌺プチオフ会開催🌺",
    "date": "2026-06-06",
    "time_open": "18:00",
    "time_start": "18:30",
    "venue": "瀬長島ビーチ",
    "price": "無料",
    "description": "【🌺プチオフ会開催🌺】 / 沖縄で花火をしながら / みんなでゆったり過ごしましょう🎆✨ / 📅6/6(土)",
    "post_url": "https://nitter.net/STAiNY_official/status/2061734772427374864#m",
    "image_url": "https://nitter.net/pic/media%2FHJzA2P1bQAAqzSA.jpg",
    "created_at": "2026-06-02T09:00:49Z"
  },
  {
    "id": "stainy-2026-06-06-free-event-a33db6ea",
    "group_id": "stainy",
    "type": "free",
    "title": "プチオフ会",
    "date": "2026-06-06",
    "time_open": "18:00",
    "time_start": "18:30",
    "venue": "瀬長島ビーチ",
    "price": "無料",
    "ticket_url": "https://nitter.net/STAiNY_official/status/2061734772427374864#m",
    "description": "【中止のお知らせ】 / 6日に開催を予定しておりました「プチオフ会」につきまして、雨予報が変わりにくい状況を踏まえ、安全面を考慮した結果、中止とさせていただくこととなりました。 / 楽しみにしてくださっていた皆さまには大変申し訳ございませんが、ご理解いただけますと幸いです。 / 何卒よろしくお願いいたします。",
    "post_url": "https://nitter.net/STAiNY_official/status/2062163958556230045#m",
    "image_url": "https://nitter.net/pic/media%2FHJzA2P1bQAAqzSA.jpg",
    "created_at": "2026-06-03T13:26:15Z"
  },
  {
    "id": "stainy-2026-06-07-okinawa-girls-girls-day2",
    "group_id": "stainy",
    "type": "live",
    "title": "OKINAWA GIRLS GIRLS",
    "date": "2026-06-07",
    "time_start": "15:10",
    "time_end": "15:35",
    "venue": "那覇文化会館 なはーと小ホール",
    "benefit_time": "15:45-16:55(D)",
    "ticket_url": "http://tiget.net/events/486726",
    "description": "各: 2s写メ券+2pt(前方+15秒動画)",
    "post_url": "https://nitter.net/STAiNY_official/status/2060316558610849853#m",
    "created_at": "2026-05-29T11:05:21Z"
  },
  {
    "id": "stainy-2026-06-10-premium-live-deadline",
    "group_id": "stainy",
    "type": "deadline",
    "title": "プレミアムライブ参加申込み締切",
    "date": "2026-06-10",
    "time_start": "12:00",
    "description": "ポイントカード250ポイント達成者向けプレミアムライブの申込み締切。",
    "ticket_url": "https://docs.google.com/forms/d/e/1FAIpQLScIsTQT0ln1r1MBL6IpAwyqffOVmpL7cc3m0sP9Tln4MpJpAQ/viewform?usp=publish-editor",
    "post_url": "https://nitter.net/STAiNY_official/status/2061800688213172410#m",
    "created_at": "2026-06-02T13:22:45Z"
  },
  {
    "id": "stainy-2026-06-12-sawayaka-date",
    "group_id": "stainy",
    "type": "live",
    "title": "爽やかデート私服公演",
    "date": "2026-06-12",
    "time_open": "19:00",
    "time_start": "19:20",
    "venue": "新宿 WALLY",
    "price": "優先3000円（2s写メ券+1pt）/ 通常1000円(D代事前徴収) / 当日+500円(各1D別)",
    "ticket_url": "https://t-dv.com/STAiNY0612",
    "description": "6/12(金) 単独公演。",
    "post_url": "https://nitter.net/STAiNY_official/status/2061403523267575825#m",
    "created_at": "2026-06-01T11:04:33Z"
  },
  {
    "id": "stainy-2026-06-12-live-event-763017f1",
    "group_id": "stainy",
    "type": "live",
    "title": "｢爽やかデート私服公演」",
    "date": "2026-06-12",
    "time_open": "19:00",
    "time_start": "19:20",
    "venue": "新宿 WALLY",
    "price": "優先3000円（2s写メ券+1pt）/通常1000円(D代事前徴収)/当日+500円(各1D別)",
    "description": "【6/12(金)単独公演】 / ｢爽やかデート私服公演」 / 🏟新宿 WALLY / 🚪開場19:00/🏁開演19:20",
    "post_url": "https://nitter.net/STAiNY_official/status/2061403523267575825#m",
    "image_url": "https://nitter.net/pic/media%2FHJuTk6laoAA3iWk.jpg",
    "created_at": "2026-06-01T11:04:33Z"
  },
  {
    "id": "stainy-2026-06-17-live---671eb10b",
    "group_id": "stainy",
    "type": "live",
    "title": "リリイベ",
    "date": "2026-06-17",
    "description": "リリイベ",
    "created_at": "2026-06-04T01:08:10.787Z"
  },
  {
    "id": "stainy-2026-06-18-live-summer-beat-4c2f47d0",
    "group_id": "stainy",
    "type": "live",
    "title": "summer beat",
    "date": "2026-06-18",
    "description": "summer beat",
    "created_at": "2026-06-04T01:08:10.788Z"
  },
  {
    "id": "stainy-2026-06-19-live---e00650f",
    "group_id": "stainy",
    "type": "live",
    "title": "リリイベ沖縄県",
    "date": "2026-06-19",
    "description": "リリイベ沖縄県",
    "created_at": "2026-06-04T01:08:10.788Z"
  },
  {
    "id": "stainy-2026-06-20-live-girls-girls-181a5020",
    "group_id": "stainy",
    "type": "live",
    "title": "GIRLS GIRLS",
    "date": "2026-06-20",
    "description": "GIRLS GIRLS",
    "created_at": "2026-06-04T01:08:10.788Z"
  },
  {
    "id": "stainy-2026-06-21-himari-birthday",
    "group_id": "stainy",
    "type": "live",
    "title": "佐々木ひまり生誕祭",
    "date": "2026-06-21",
    "time_open": "10:30",
    "time_start": "11:00",
    "venue": "下北沢シャングリラ",
    "benefit_time": "特典会別会場: 後日ご案内",
    "price": "優先3000円 / 通常2000円 / 当日2500円(各1D別)",
    "ticket_url": "https://ticketdive.com/event/STAiNY0621",
    "description": "6/21(日) 生誕祭情報。",
    "post_url": "https://nitter.net/STAiNY_official/status/2061749699728863301#m",
    "created_at": "2026-06-02T10:00:08Z"
  },
  {
    "id": "stainy-2026-06-21-live-event-bc1c792c",
    "group_id": "stainy",
    "type": "live",
    "title": "「佐々木ひまり生誕祭」",
    "date": "2026-06-21",
    "time_open": "10:30",
    "time_start": "11:00",
    "venue": "下北沢シャングリラ",
    "price": "優先3000円/通常2000円/当日2500円(各1D別)",
    "description": "【6/21(日)生誕祭情報🎂🧡ྀི】 / 「佐々木ひまり生誕祭」 / 🏟下北沢シャングリラ / 🚪開場10:30🏁開演11:00",
    "post_url": "https://nitter.net/STAiNY_official/status/2061749699728863301#m",
    "image_url": "https://nitter.net/pic/media%2FHJzOaMIbIAEHNa6.jpg",
    "created_at": "2026-06-02T10:00:08Z"
  },
  {
    "id": "stainy-2026-06-21-live-event-cf1c0a4d",
    "group_id": "stainy",
    "type": "live",
    "title": "佐々木ひまり生誕祭",
    "date": "2026-06-21",
    "time_open": "10:30",
    "time_start": "11:00",
    "venue": "下北沢シャングリラ",
    "price": "優先3000円/通常2000円/当日2500円(各1D別)",
    "description": "【6/21(日)生誕祭情報🎂🧡ྀི】 / 「佐々木ひまり生誕祭」 / 🏟下北沢シャングリラ / 🚪開場10:30🏁開演11:00",
    "post_url": "https://nitter.net/STAiNY_official/status/2061749699728863301#m",
    "image_url": "https://nitter.net/pic/media%2FHJzOaMIbIAEHNa6.jpg",
    "created_at": "2026-06-02T10:00:08Z"
  },
  {
    "id": "stainy-2026-06-21-live-girls-girls-2353cdc1",
    "group_id": "stainy",
    "type": "live",
    "title": "GIRLS GIRLS",
    "date": "2026-06-21",
    "description": "GIRLS GIRLS",
    "created_at": "2026-06-04T01:08:10.788Z"
  },
  {
    "id": "stainy-2026-06-23-dont-you-liar-release",
    "group_id": "stainy",
    "type": "release",
    "title": "1stアルバム「ドンチューライアー」発売・配信開始",
    "date": "2026-06-23",
    "description": "STAiNY 1stアルバム「ドンチューライアー」発売＆配信開始。",
    "ticket_url": "https://entabaonline.stores.jp/?category_id=69cf44b98474878675f5b41c",
    "post_url": "https://nitter.net/STAiNY_official/status/2061791566658957332#m",
    "created_at": "2026-06-02T12:46:30Z"
  },
  {
    "id": "stainy-2026-06-23-release-stainy-f3f5a752",
    "group_id": "stainy",
    "type": "release",
    "title": "👾明日のSTAiNY✨",
    "date": "2026-06-23",
    "description": "／ / 👾明日のSTAiNY✨ / 💽1stアルバム「ドンチューライアー」 / 🚀リリースイベント東京編🤖",
    "ticket_url": "https://entabaonline.stores.jp/?category_id=69cf44b98474878675f5b41c",
    "post_url": "https://nitter.net/STAiNY_official/status/2061791566658957332#m",
    "image_url": "https://nitter.net/pic/media%2FHJz0fNFbAAAq4QO.jpg",
    "created_at": "2026-06-02T12:46:30Z"
  },
  {
    "id": "stainy-2026-06-23-release-stainy-c801fea4",
    "group_id": "stainy",
    "type": "release",
    "title": "👾STAiNY「ドンチューライアー」",
    "date": "2026-06-23",
    "description": "／ / 👾STAiNY「ドンチューライアー」 / 📺tvk「音楽缶」 / 🗓6月度オープニングテーマに決定‼️",
    "ticket_url": "https://www.tvk-yokohama.com/ongakukan/index2.php",
    "post_url": "https://nitter.net/STAiNY_official/status/2061440243929403733#m",
    "image_url": "https://nitter.net/pic/media%2FHJu0-cbbwAEv1vv.jpg",
    "created_at": "2026-06-01T13:30:28Z"
  },
  {
    "id": "stainy-2026-06-23-release-stainy-1st-801352f7",
    "group_id": "stainy",
    "type": "release",
    "title": "💽STAiNY 1stアルバム",
    "date": "2026-06-23",
    "description": "／ / 💽STAiNY 1stアルバム / 「ドンチューライアー」 / リリースイベント追加日程&TT解禁✨",
    "post_url": "https://nitter.net/STAiNY_official/status/2061428750626283537#m",
    "image_url": "https://nitter.net/pic/media%2FHJuqg3saAAApWQj.jpg",
    "created_at": "2026-06-01T12:44:48Z"
  },
  {
    "id": "stainy-2026-06-23-release-stainy-5f85e45f",
    "group_id": "stainy",
    "type": "release",
    "title": "👾STAiNY「ドンチューライアー」",
    "date": "2026-06-23",
    "description": "／ / 👾STAiNY「ドンチューライアー」 / 📺MBS「かまいたちの知らんけど」 / 🗓6月度エンディングテーマに決定‼️",
    "post_url": "https://nitter.net/STAiNY_official/status/2060760752068481048#m",
    "image_url": "https://nitter.net/pic/media%2FHJlK-7MaEAA2HjW.jpg",
    "created_at": "2026-05-30T16:30:25Z"
  },
  {
    "id": "stainy-2026-06-23-release-event-952a3fdb",
    "group_id": "stainy",
    "type": "release",
    "title": "ドンチューライアー",
    "date": "2026-06-23",
    "description": "／ / 👾明日のSTAiNY✨ / 💽1stアルバム「ドンチューライアー」 / 🚀リリースイベント東京編🤖",
    "ticket_url": "https://entabaonline.stores.jp/?category_id=69cf44b98474878675f5b41c",
    "post_url": "https://nitter.net/STAiNY_official/status/2061791566658957332#m",
    "image_url": "https://nitter.net/pic/media%2FHJz0fNFbAAAq4QO.jpg",
    "created_at": "2026-06-02T12:46:30Z"
  },
  {
    "id": "stainy-2026-06-23-release-event-726b4cf6",
    "group_id": "stainy",
    "type": "release",
    "title": "ドンチューライアー",
    "date": "2026-06-23",
    "description": "／ / 👾STAiNY「ドンチューライアー」 / 📺tvk「音楽缶」 / 🗓6月度オープニングテーマに決定‼️",
    "ticket_url": "https://www.tvk-yokohama.com/ongakukan/index2.php",
    "post_url": "https://nitter.net/STAiNY_official/status/2061440243929403733#m",
    "image_url": "https://nitter.net/pic/media%2FHJu0-cbbwAEv1vv.jpg",
    "created_at": "2026-06-01T13:30:28Z"
  },
  {
    "id": "stainy-2026-06-23-release-event-00dd7220",
    "group_id": "stainy",
    "type": "release",
    "title": "ドンチューライアー",
    "date": "2026-06-23",
    "description": "／ / 💽STAiNY 1stアルバム / 「ドンチューライアー」 / リリースイベント追加日程&TT解禁✨",
    "post_url": "https://nitter.net/STAiNY_official/status/2061428750626283537#m",
    "image_url": "https://nitter.net/pic/media%2FHJuqg3saAAApWQj.jpg",
    "created_at": "2026-06-01T12:44:48Z"
  },
  {
    "id": "stainy-2026-06-23-release-event-3877e8a3",
    "group_id": "stainy",
    "type": "release",
    "title": "ドンチューライアー",
    "date": "2026-06-23",
    "description": "／ / 👾STAiNY「ドンチューライアー」 / 📺MBS「かまいたちの知らんけど」 / 🗓6月度エンディングテーマに決定‼️",
    "post_url": "https://nitter.net/STAiNY_official/status/2060760752068481048#m",
    "image_url": "https://nitter.net/pic/media%2FHJlK-7MaEAA2HjW.jpg",
    "created_at": "2026-05-30T16:30:25Z"
  },
  {
    "id": "stainy-2026-06-26-sweet-partt",
    "group_id": "stainy",
    "type": "live",
    "title": "SWEET PARTT",
    "date": "2026-06-26",
    "time_open": "16:45",
    "time_start": "17:15",
    "venue": "白金高輪SELENE b2",
    "benefit_time": "2s写メ券+1pt(前方+15秒動画)",
    "ticket_url": "https://livepocket.jp/e/sweetparty_selene",
    "description": "Sweet Alley 主催の対バン。",
    "post_url": "https://nitter.net/STAiNY_official/status/2060323359335063633#m",
    "created_at": "2026-05-29T11:32:22Z"
  },
  {
    "id": "stainy-2026-06-26-live-sweet-partt-93f6fefa",
    "group_id": "stainy",
    "type": "live",
    "title": "「SWEET PARTT」",
    "date": "2026-06-26",
    "time_open": "16:45",
    "time_start": "17:15",
    "venue": "白金高輪SELENE b2",
    "description": "【6/26(金)対バン情報✨】 / 「SWEET PARTT」 / 🏟白金高輪SELENE b2 / 🚪開場16:45/🏁開演17:15",
    "post_url": "https://nitter.net/STAiNY_official/status/2060323359335063633#m",
    "image_url": "https://nitter.net/pic/media%2FHJe9K9kbMAA3TAn.jpg",
    "created_at": "2026-05-29T11:32:22Z"
  },
  {
    "id": "stainy-2026-06-26-live-sweet-partt-4972b688",
    "group_id": "stainy",
    "type": "live",
    "title": "SWEET PARTT",
    "date": "2026-06-26",
    "time_open": "16:45",
    "time_start": "17:15",
    "venue": "白金高輪SELENE b2",
    "description": "【6/26(金)対バン情報✨】 / 「SWEET PARTT」 / 🏟白金高輪SELENE b2 / 🚪開場16:45/🏁開演17:15",
    "post_url": "https://nitter.net/STAiNY_official/status/2060323359335063633#m",
    "image_url": "https://nitter.net/pic/media%2FHJe9K9kbMAA3TAn.jpg",
    "created_at": "2026-05-29T11:32:22Z"
  },
  {
    "id": "stainy-2026-06-26-live-stargazer-sg--79d4476d",
    "group_id": "stainy",
    "type": "live",
    "title": "StarGazer-SG-",
    "date": "2026-06-26",
    "description": "StarGazer-SG-",
    "created_at": "2026-06-04T01:08:10.788Z"
  },
  {
    "id": "stainy-2026-07-06-live---52d08538",
    "group_id": "stainy",
    "type": "live",
    "title": "対バン名古屋",
    "date": "2026-07-06",
    "description": "対バン名古屋",
    "created_at": "2026-06-04T01:09:30.191Z"
  },
  {
    "id": "stainy-2026-07-07-live-neo-kassen-11b3a7dd",
    "group_id": "stainy",
    "type": "live",
    "title": "NEO KASSEN",
    "date": "2026-07-07",
    "description": "NEO KASSEN",
    "created_at": "2026-06-04T01:09:30.191Z"
  },
  {
    "id": "stainy-2026-07-08-live-sweet-party-24964c81",
    "group_id": "stainy",
    "type": "live",
    "title": "SWEET PARTY",
    "date": "2026-07-08",
    "description": "SWEET PARTY",
    "created_at": "2026-06-04T01:09:30.191Z"
  },
  {
    "id": "stainy-2026-07-11-live---445807aa",
    "group_id": "stainy",
    "type": "live",
    "title": "リリースイベント",
    "date": "2026-07-11",
    "description": "リリースイベント",
    "created_at": "2026-06-04T01:09:30.191Z"
  },
  {
    "id": "stainy-2026-07-12-live-stay-tune-4man-3fe5f1ac",
    "group_id": "stainy",
    "type": "live",
    "title": "STAY TUNE! 4MAN",
    "date": "2026-07-12",
    "description": "STAY TUNE! 4MAN",
    "created_at": "2026-06-04T01:09:30.191Z"
  },
  {
    "id": "stainy-2026-07-14-live--upgate--3f0c823b",
    "group_id": "stainy",
    "type": "live",
    "title": "歌舞伎町UPGATE↑",
    "date": "2026-07-14",
    "description": "歌舞伎町UPGATE↑",
    "created_at": "2026-06-04T01:09:30.191Z"
  },
  {
    "id": "stainy-2026-07-18-live---8ba2395",
    "group_id": "stainy",
    "type": "live",
    "title": "対バン",
    "date": "2026-07-18",
    "description": "対バン",
    "created_at": "2026-06-04T01:09:30.191Z"
  },
  {
    "id": "stainy-2026-07-19-live---4688cd2a",
    "group_id": "stainy",
    "type": "live",
    "title": "リリースツアー",
    "date": "2026-07-19",
    "description": "リリースツアー",
    "created_at": "2026-06-04T01:09:30.191Z"
  },
  {
    "id": "stainy-2026-07-19-live---1470b276",
    "group_id": "stainy",
    "type": "live",
    "title": "対バン",
    "date": "2026-07-19",
    "description": "対バン",
    "created_at": "2026-06-04T01:09:30.191Z"
  },
  {
    "id": "stainy-2026-08-11-live-yoru-fes-rock-fes-782d8479",
    "group_id": "stainy",
    "type": "live",
    "title": "YORU-FESよるあみなりのROCK FES",
    "date": "2026-08-11",
    "description": "YORU-FESよるあみなりのROCK FES",
    "created_at": "2026-06-04T01:08:10.788Z"
  },
  {
    "id": "stainy-2026-08-13-live---28b886bb",
    "group_id": "stainy",
    "type": "live",
    "title": "リリイベ",
    "date": "2026-08-13",
    "description": "リリイベ",
    "created_at": "2026-06-04T01:08:10.788Z"
  },
  {
    "id": "stainy-2026-08-14-live---7ccecacd",
    "group_id": "stainy",
    "type": "live",
    "title": "単独公演",
    "date": "2026-08-14",
    "description": "単独公演",
    "created_at": "2026-06-04T01:08:10.788Z"
  },
  {
    "id": "stainy-2026-08-15-live--vv--3c9b5ac6",
    "group_id": "stainy",
    "type": "live",
    "title": "リリイベVV札幌",
    "date": "2026-08-15",
    "description": "リリイベVV札幌",
    "created_at": "2026-06-04T01:08:10.788Z"
  },
  {
    "id": "stainy-2026-08-16-live---20a52205",
    "group_id": "stainy",
    "type": "live",
    "title": "リリースツアー北海道",
    "date": "2026-08-16",
    "description": "リリースツアー北海道",
    "created_at": "2026-06-04T01:08:10.788Z"
  },
  {
    "id": "stainy-2026-09-01-live-kyun-fes-tokyo-vol-2-7ee41b99",
    "group_id": "stainy",
    "type": "live",
    "title": "KYUN-FES TOKYO vol.2",
    "date": "2026-09-01",
    "description": "KYUN-FES TOKYO vol.2",
    "created_at": "2026-06-04T01:09:30.191Z"
  },
  {
    "id": "stainy-2026-09-05-live-fes-tive-presents--d791819",
    "group_id": "stainy",
    "type": "live",
    "title": "FES☆TIVE Presents「波響祭」",
    "date": "2026-09-05",
    "description": "FES☆TIVE Presents「波響祭」",
    "created_at": "2026-06-04T01:09:30.191Z"
  },
  {
    "id": "stainy-2026-09-06-live-idol-storm-5c9ac74",
    "group_id": "stainy",
    "type": "live",
    "title": "IDOL STORM",
    "date": "2026-09-06",
    "description": "IDOL STORM",
    "created_at": "2026-06-04T01:09:30.191Z"
  },
  {
    "id": "stainy-2026-09-12-live---6158d92b",
    "group_id": "stainy",
    "type": "live",
    "title": "リリースイベント",
    "date": "2026-09-12",
    "description": "リリースイベント",
    "created_at": "2026-06-04T01:09:30.191Z"
  },
  {
    "id": "stainy-2026-10-06-live---29e91c7c",
    "group_id": "stainy",
    "type": "live",
    "title": "対バン",
    "date": "2026-10-06",
    "description": "対バン",
    "created_at": "2026-06-04T01:08:10.788Z"
  },
  {
    "id": "stainy-2026-10-07-live---359fab5d",
    "group_id": "stainy",
    "type": "live",
    "title": "対バン",
    "date": "2026-10-07",
    "description": "対バン",
    "created_at": "2026-06-04T01:08:10.788Z"
  },
  {
    "id": "stainy-2026-10-09-live---4d0cc91f",
    "group_id": "stainy",
    "type": "live",
    "title": "対バン",
    "date": "2026-10-09",
    "description": "対バン",
    "created_at": "2026-06-04T01:08:10.788Z"
  },
  {
    "id": "stainy-2026-10-10-live---6413131a",
    "group_id": "stainy",
    "type": "live",
    "title": "リリイベ東京",
    "date": "2026-10-10",
    "description": "リリイベ東京",
    "created_at": "2026-06-04T01:08:10.788Z"
  },
  {
    "id": "stainy-2026-10-16-live---1f1d512f",
    "group_id": "stainy",
    "type": "live",
    "title": "リリイベ",
    "date": "2026-10-16",
    "description": "リリイベ",
    "created_at": "2026-06-04T01:08:10.788Z"
  },
  {
    "id": "stainy-2026-10-28-live---2b2a3ed4",
    "group_id": "stainy",
    "type": "live",
    "title": "#フライングサマー",
    "date": "2026-10-28",
    "description": "#フライングサマー",
    "created_at": "2026-06-04T01:09:30.191Z"
  },
  {
    "id": "stainy-2026-10-31-live---4e2a132d",
    "group_id": "stainy",
    "type": "live",
    "title": "リリイベ大阪",
    "date": "2026-10-31",
    "description": "リリイベ大阪",
    "created_at": "2026-06-04T01:09:30.191Z"
  },
  {
    "id": "stainy-2026-11-01-live---7fffb493",
    "group_id": "stainy",
    "type": "live",
    "title": "リリースツアー大阪",
    "date": "2026-11-01",
    "description": "リリースツアー大阪",
    "created_at": "2026-06-04T01:09:30.191Z"
  },
  {
    "id": "stainy-2026-11-30-live---661c71b0",
    "group_id": "stainy",
    "type": "live",
    "title": "リリースツアー東京ファイナル",
    "date": "2026-11-30",
    "description": "リリースツアー東京ファイナル",
    "created_at": "2026-06-04T01:08:10.788Z"
  },
  {
    "id": "stainy-2026-12-01-live---4b8ae115",
    "group_id": "stainy",
    "type": "live",
    "title": "リリイベ",
    "date": "2026-12-01",
    "description": "リリイベ",
    "created_at": "2026-06-04T01:08:10.788Z"
  },
  {
    "id": "stainy-2026-12-02-live-parad-i-se-vol-5-2-s-7f6bd5ef",
    "group_id": "stainy",
    "type": "live",
    "title": "PARAD-i-SE Vol.5 -2周年ワンマン前SP！",
    "date": "2026-12-02",
    "description": "PARAD-i-SE Vol.5 -2周年ワンマン前SP！",
    "created_at": "2026-06-04T01:08:10.788Z"
  },
  {
    "id": "stainy-2026-12-04-live---3575f1b8",
    "group_id": "stainy",
    "type": "live",
    "title": "対バン",
    "date": "2026-12-04",
    "description": "対バン",
    "created_at": "2026-06-04T01:08:10.788Z"
  },
  {
    "id": "stainy-2026-12-05-live---25c1ff8a",
    "group_id": "stainy",
    "type": "live",
    "title": "リリイベ東京",
    "date": "2026-12-05",
    "description": "リリイベ東京",
    "created_at": "2026-06-04T01:08:10.788Z"
  },
  {
    "id": "stainy-2026-12-06-live---4cfc7467",
    "group_id": "stainy",
    "type": "live",
    "title": "名古屋",
    "date": "2026-12-06",
    "description": "名古屋",
    "created_at": "2026-06-04T01:08:10.788Z"
  },
  {
    "id": "stainy-2026-12-24-live---392300e4",
    "group_id": "stainy",
    "type": "live",
    "title": "でびぱっぱ",
    "date": "2026-12-24",
    "description": "でびぱっぱ",
    "created_at": "2026-06-04T01:09:30.191Z"
  },
  {
    "id": "stainy-2026-12-25-live--vv--475b2621",
    "group_id": "stainy",
    "type": "live",
    "title": "リリイベ VV渋谷",
    "date": "2026-12-25",
    "description": "リリイベ VV渋谷",
    "created_at": "2026-06-04T01:09:30.191Z"
  },
  {
    "id": "stainy-2026-12-26-live---232506d7",
    "group_id": "stainy",
    "type": "live",
    "title": "リリイベ 埼玉コクーシンシティ",
    "date": "2026-12-26",
    "description": "リリイベ 埼玉コクーシンシティ",
    "created_at": "2026-06-04T01:09:30.191Z"
  },
  {
    "id": "stainy-2026-12-27-live---287b1149",
    "group_id": "stainy",
    "type": "live",
    "title": "リリイベ タワレコ新宿",
    "date": "2026-12-27",
    "description": "リリイベ タワレコ新宿",
    "created_at": "2026-06-04T01:09:30.191Z"
  },
  {
    "id": "stainy-2027-01-02-live---353e98bb",
    "group_id": "stainy",
    "type": "live",
    "title": "フライングサマー 後夜祭",
    "date": "2027-01-02",
    "description": "フライングサマー 後夜祭",
    "created_at": "2026-06-04T01:09:30.191Z"
  },
  {
    "id": "stainy-2027-01-30-live---36bc9032",
    "group_id": "stainy",
    "type": "live",
    "title": "対バン",
    "date": "2027-01-30",
    "description": "対バン",
    "created_at": "2026-06-04T01:08:10.788Z"
  },
  {
    "id": "stainy-2027-01-31-live---42731f13",
    "group_id": "stainy",
    "type": "live",
    "title": "対バン",
    "date": "2027-01-31",
    "description": "対バン",
    "created_at": "2026-06-04T01:08:10.788Z"
  }
]
